image_processing/__init__.py
image_processing/processing/__init__.py
image_processing/processing/combination.py
image_processing/processing/transformation.py
image_processing/utils/__init__.py
image_processing/utils/io.py
image_processing/utils/plot.py
virtual_image_clara-0.0.1.dist-info/METADATA
virtual_image_clara-0.0.1.dist-info/WHEEL
virtual_image_clara-0.0.1.dist-info/top_level.txt
virtual_image_clara-0.0.1.dist-info/RECORD
