Metadata-Version: 2.1
Name: virtual-image-clara
Version: 0.0.1
Summary: Image Processing Package using skimage
Home-page: https://github.com/claraalcina/projeto-image-processing-package.git
Author: Clara Guandalini
License: UNKNOWN
Platform: UNKNOWN
Requires-Python: >=3.8
Requires-Dist: matplotlib
Requires-Dist: numpy
Requires-Dist: scikit-image (>=0.16.1)
